gym_backgammon/__init__.py
gym_backgammon/envs/__init__.py
gym_backgammon/envs/backgammon.py
gym_backgammon/envs/backgammon_env.py
gym_backgammon/envs/rendering.py
gym_backgammon-0.0.1.dist-info/LICENSE
gym_backgammon-0.0.1.dist-info/METADATA
gym_backgammon-0.0.1.dist-info/WHEEL
gym_backgammon-0.0.1.dist-info/top_level.txt
gym_backgammon-0.0.1.dist-info/RECORD
