Metadata-Version: 2.2
Name: gym_backgammon
Version: 0.0.1
License-File: LICENSE
Requires-Dist: gym
Dynamic: requires-dist
